{
  "mode": "2p-h2h-single-deal-continuous",
  "games": 300,
  "v7Wins": 238,
  "v60Wins": 62,
  "v7WinRate": 0.7933333333333333,
  "ci95": {
    "p": 0.7933333333333333,
    "lo": 0.7439440144288736,
    "hi": 0.8353051733057882
  },
  "target": 0.75,
  "passed": true,
  "ms": 1785735,
  "v7": {
    "id": "v7.0-combat-twos-vs-v60",
    "stamped": "2026-07-11T08:00:00-07:00",
    "label": "Grandmaster v7.0"
  },
  "v60": {
    "id": "v6.0-frozen-baseline",
    "stamped": "2026-07-11T01:00:00-07:00",
    "label": "Grandmaster v6.0 (frozen)"
  },
  "v7Opts": {
    "difficulty": "hard",
    "timeMs": 100,
    "iterations": 120,
    "maxSims": 280,
    "brTrials": 48,
    "bestResponse": true,
    "useSearch": true,
    "perfectInfo": true,
    "hiddenInfo": false,
    "maxBranch": 16,
    "mode": "auto"
  },
  "v60Opts": {
    "difficulty": "easy",
    "iterations": 0,
    "mode": "expert"
  },
  "opponentFreeze": "policies/v60-ai.js + policies/v60-search.js",
  "seed0": 20260711,
  "checkpoints": [
    {
      "games": 25,
      "v7Wins": 20,
      "v7WinRate": 0.8,
      "ci95": {
        "p": 0.8,
        "lo": 0.6086866446346176,
        "hi": 0.9113954589934752
      },
      "ms": 114203,
      "gps": 0.21890843497981663
    },
    {
      "games": 50,
      "v7Wins": 38,
      "v7WinRate": 0.76,
      "ci95": {
        "p": 0.76,
        "lo": 0.6258705062480764,
        "hi": 0.8570274759812778
      },
      "ms": 229012,
      "gps": 0.21832917052381534
    },
    {
      "games": 75,
      "v7Wins": 55,
      "v7WinRate": 0.7333333333333333,
      "ci95": {
        "p": 0.7333333333333333,
        "lo": 0.6236898715426942,
        "hi": 0.8202382070351124
      },
      "ms": 349480,
      "gps": 0.21460455533936132
    },
    {
      "games": 100,
      "v7Wins": 75,
      "v7WinRate": 0.75,
      "ci95": {
        "p": 0.75,
        "lo": 0.6569535362992417,
        "hi": 0.8245490599627574
      },
      "ms": 470386,
      "gps": 0.2125913611374488
    },
    {
      "games": 125,
      "v7Wins": 96,
      "v7WinRate": 0.768,
      "ci95": {
        "p": 0.768,
        "lo": 0.6866850458237092,
        "hi": 0.8333333333333334
      },
      "ms": 560865,
      "gps": 0.22287003111265635
    },
    {
      "games": 150,
      "v7Wins": 116,
      "v7WinRate": 0.7733333333333333,
      "ci95": {
        "p": 0.7733333333333333,
        "lo": 0.6999966119167443,
        "hi": 0.8330191653502628
      },
      "ms": 737253,
      "gps": 0.20345797168678864
    },
    {
      "games": 175,
      "v7Wins": 137,
      "v7WinRate": 0.7828571428571428,
      "ci95": {
        "p": 0.7828571428571428,
        "lo": 0.7160488807442318,
        "hi": 0.8375136013628395
      },
      "ms": 839759,
      "gps": 0.20839312231247298
    },
    {
      "games": 200,
      "v7Wins": 156,
      "v7WinRate": 0.78,
      "ci95": {
        "p": 0.78,
        "lo": 0.7176107720803744,
        "hi": 0.8318354646053661
      },
      "ms": 1093481,
      "gps": 0.18290212632866965
    },
    {
      "games": 225,
      "v7Wins": 175,
      "v7WinRate": 0.7777777777777778,
      "ci95": {
        "p": 0.7777777777777778,
        "lo": 0.7190477891233493,
        "hi": 0.8271815677767946
      },
      "ms": 1176260,
      "gps": 0.19128423987893833
    },
    {
      "games": 250,
      "v7Wins": 196,
      "v7WinRate": 0.784,
      "ci95": {
        "p": 0.784,
        "lo": 0.7288955001859428,
        "hi": 0.8305084745762712
      },
      "ms": 1433714,
      "gps": 0.17437229461384907
    },
    {
      "games": 275,
      "v7Wins": 217,
      "v7WinRate": 0.7890909090909091,
      "ci95": {
        "p": 0.7890909090909091,
        "lo": 0.7370589685761442,
        "hi": 0.833157240196148
      },
      "ms": 1523775,
      "gps": 0.18047283883775492
    },
    {
      "games": 300,
      "v7Wins": 238,
      "v7WinRate": 0.7933333333333333,
      "ci95": {
        "p": 0.7933333333333333,
        "lo": 0.7439440144288736,
        "hi": 0.8353051733057882
      },
      "ms": 1785734,
      "gps": 0.16799814530047588
    }
  ]
}