{
  "url": "https://api.github.com/repos/jvhoang/tieng-len/issues/82",
  "repository_url": "https://api.github.com/repos/jvhoang/tieng-len",
  "labels_url": "https://api.github.com/repos/jvhoang/tieng-len/issues/82/labels{/name}",
  "comments_url": "https://api.github.com/repos/jvhoang/tieng-len/issues/82/comments",
  "events_url": "https://api.github.com/repos/jvhoang/tieng-len/issues/82/events",
  "html_url": "https://github.com/jvhoang/tieng-len/issues/82",
  "id": 4863137849,
  "node_id": "I_kwDOTIz2w88AAAABId2YOQ",
  "number": 82,
  "title": "playlog | 2p | human-win | 2026-07-11T16:20:18 | g_mrgki4l9_0vcopel6",
  "user": {
    "login": "jvhoang",
    "id": 70288758,
    "node_id": "MDQ6VXNlcjcwMjg4NzU4",
    "avatar_url": "https://avatars.githubusercontent.com/u/70288758?v=4",
    "gravatar_id": "",
    "url": "https://api.github.com/users/jvhoang",
    "html_url": "https://github.com/jvhoang",
    "followers_url": "https://api.github.com/users/jvhoang/followers",
    "following_url": "https://api.github.com/users/jvhoang/following{/other_user}",
    "gists_url": "https://api.github.com/users/jvhoang/gists{/gist_id}",
    "starred_url": "https://api.github.com/users/jvhoang/starred{/owner}{/repo}",
    "subscriptions_url": "https://api.github.com/users/jvhoang/subscriptions",
    "organizations_url": "https://api.github.com/users/jvhoang/orgs",
    "repos_url": "https://api.github.com/users/jvhoang/repos",
    "events_url": "https://api.github.com/users/jvhoang/events{/privacy}",
    "received_events_url": "https://api.github.com/users/jvhoang/received_events",
    "type": "User",
    "user_view_type": "public",
    "site_admin": false
  },
  "labels": [
    {
      "id": 11486684160,
      "node_id": "LA_kwDOTIz2w88AAAACrKjkAA",
      "url": "https://api.github.com/repos/jvhoang/tieng-len/labels/play-log",
      "name": "play-log",
      "color": "c9a227",
      "default": false,
      "description": "Tiến Lên live play logs (auto-published for AI analysis)"
    }
  ],
  "state": "open",
  "locked": false,
  "assignees": [],
  "milestone": null,
  "comments": 0,
  "created_at": "2026-07-11T16:20:18Z",
  "updated_at": "2026-07-11T16:20:18Z",
  "closed_at": null,
  "assignee": null,
  "author_association": "OWNER",
  "active_lock_reason": null,
  "sub_issues_summary": {
    "total": 0,
    "completed": 0,
    "percent_completed": 0
  },
  "issue_dependencies_summary": {
    "blocked_by": 0,
    "total_blocked_by": 0,
    "blocking": 0,
    "total_blocking": 0
  },
  "body": "<!-- TIENLEN_PLAYLOG_V1 -->\n\n**Mode:** vsAI · **AI:** grandmaster · **Human won:** true\n\n```json\n{\"schemaVersion\":1,\"id\":\"g_mrgki4l9_0vcopel6\",\"startedAt\":\"2026-07-11T16:17:10.077Z\",\"endedAt\":\"2026-07-11T16:20:18.311Z\",\"mode\":\"vsAI\",\"vsAI\":true,\"numPlayers\":2,\"humanSeats\":[0],\"aiSeats\":[1],\"aiDifficulty\":\"grandmaster\",\"aiBuild\":null,\"seed\":1783786630077,\"siteBuild\":\"20260711c\",\"env\":{\"schemaVersion\":1,\"capturedAt\":\"2026-07-11T16:17:10.078Z\",\"href\":\"https://jvhoang.github.io/tieng-len/\",\"origin\":\"https://jvhoang.github.io\",\"userAgent\":\"Mozilla/5.0 (iPhone; CPU iPhone OS 18_7 like Mac OS X) AppleWebKit/605.1.15 (KHTML, like Gecko) Version/26.5 Mobile/15E148 Safari/604.1\",\"language\":\"en-US\",\"screen\":{\"w\":440,\"h\":956}},\"deal\":{\"hands\":[[{\"rank\":7,\"suit\":2},{\"rank\":1,\"suit\":3},{\"rank\":10,\"suit\":3},{\"rank\":0,\"suit\":0},{\"rank\":2,\"suit\":1},{\"rank\":8,\"suit\":2},{\"rank\":1,\"suit\":0},{\"rank\":9,\"suit\":2},{\"rank\":4,\"suit\":3},{\"rank\":12,\"suit\":3},{\"rank\":8,\"suit\":0},{\"rank\":11,\"suit\":0},{\"rank\":2,\"suit\":3}],[{\"rank\":5,\"suit\":2},{\"rank\":0,\"suit\":3},{\"rank\":3,\"suit\":2},{\"rank\":2,\"suit\":0},{\"rank\":0,\"suit\":2},{\"rank\":8,\"suit\":1},{\"rank\":3,\"suit\":1},{\"rank\":6,\"suit\":3},{\"rank\":6,\"suit\":1},{\"rank\":11,\"suit\":2},{\"rank\":8,\"suit\":3},{\"rank\":10,\"suit\":1},{\"rank\":9,\"suit\":0}]],\"firstPlayer\":0,\"firstLeadCard\":{\"rank\":0,\"suit\":0},\"isFirstLead\":true},\"openingSnapshot\":[{\"seat\":0,\"hand\":[{\"rank\":7,\"suit\":2},{\"rank\":1,\"suit\":3},{\"rank\":10,\"suit\":3},{\"rank\":0,\"suit\":0},{\"rank\":2,\"suit\":1},{\"rank\":8,\"suit\":2},{\"rank\":1,\"suit\":0},{\"rank\":9,\"suit\":2},{\"rank\":4,\"suit\":3},{\"rank\":12,\"suit\":3},{\"rank\":8,\"suit\":0},{\"rank\":11,\"suit\":0},{\"rank\":2,\"suit\":3}],\"handSize\":13,\"passed\":false,\"finished\":false},{\"seat\":1,\"hand\":[{\"rank\":5,\"suit\":2},{\"rank\":0,\"suit\":3},{\"rank\":3,\"suit\":2},{\"rank\":2,\"suit\":0},{\"rank\":0,\"suit\":2},{\"rank\":8,\"suit\":1},{\"rank\":3,\"suit\":1},{\"rank\":6,\"suit\":3},{\"rank\":6,\"suit\":1},{\"rank\":11,\"suit\":2},{\"rank\":8,\"suit\":3},{\"rank\":10,\"suit\":1},{\"rank\":9,\"suit\":0}],\"handSize\":13,\"passed\":false,\"finished\":false}],\"events\":[{\"i\":0,\"t\":4,\"wall\":\"2026-07-11T16:17:10.081Z\",\"type\":\"game_start\",\"actor\":\"system\",\"seat\":null,\"handSizes\":[13,13],\"currentPlayer\":0,\"isFirstLead\":true,\"firstLeadCard\":{\"rank\":0,\"suit\":0}},{\"i\":1,\"t\":109580,\"wall\":\"2026-07-11T16:18:59.657Z\",\"type\":\"play\",\"seat\":0,\"actor\":\"human\",\"cards\":[{\"rank\":1,\"suit\":3},{\"rank\":0,\"suit\":0},{\"rank\":2,\"suit\":1}],\"cardsSig\":\"0,7,9\",\"combo\":{\"type\":\"seq\",\"cards\":[{\"rank\":2,\"suit\":1},{\"rank\":1,\"suit\":3},{\"rank\":0,\"suit\":0}],\"top\":{\"rank\":2,\"suit\":1},\"size\":3},\"handBefore\":[{\"rank\":7,\"suit\":2},{\"rank\":1,\"suit\":3},{\"rank\":10,\"suit\":3},{\"rank\":0,\"suit\":0},{\"rank\":2,\"suit\":1},{\"rank\":8,\"suit\":2},{\"rank\":1,\"suit\":0},{\"rank\":9,\"suit\":2},{\"rank\":4,\"suit\":3},{\"rank\":12,\"suit\":3},{\"rank\":8,\"suit\":0},{\"rank\":11,\"suit\":0},{\"rank\":2,\"suit\":3}],\"handSizesBefore\":[13,13],\"handSizesAfter\":[10,13],\"currentComboBefore\":null,\"currentComboAfter\":{\"type\":\"seq\",\"cards\":[{\"rank\":2,\"suit\":1},{\"rank\":1,\"suit\":3},{\"rank\":0,\"suit\":0}],\"top\":{\"rank\":2,\"suit\":1},\"size\":3},\"currentPlayerBefore\":0,\"currentPlayerAfter\":1,\"isFirstLead\":true,\"passedFlagsBefore\":[false,false],\"finishedFlagsAfter\":[false,false],\"legalsCount\":5,\"legals\":[[{\"rank\":0,\"suit\":0}],[{\"rank\":0,\"suit\":0},{\"rank\":1,\"suit\":3},{\"rank\":2,\"suit\":1}],[{\"rank\":0,\"suit\":0},{\"rank\":1,\"suit\":3},{\"rank\":2,\"suit\":3}],[{\"rank\":0,\"suit\":0},{\"rank\":1,\"suit\":0},{\"rank\":2,\"suit\":1}],[{\"rank\":0,\"suit\":0},{\"rank\":1,\"suit\":0},{\"rank\":2,\"suit\":3}]],\"publicHistoryLen\":0,\"humanThinkMs\":109573,\"ai\":null,\"note\":null,\"roundOver\":false,\"finishOrder\":[]},{\"i\":2,\"t\":109878,\"wall\":\"2026-07-11T16:18:59.955Z\",\"type\":\"play\",\"seat\":1,\"actor\":\"ai\",\"cards\":[{\"rank\":8,\"suit\":1},{\"rank\":9,\"suit\":0},{\"rank\":10,\"suit\":1}],\"cardsSig\":\"33,36,41\",\"combo\":{\"type\":\"seq\",\"cards\":[{\"rank\":10,\"suit\":1},{\"rank\":9,\"suit\":0},{\"rank\":8,\"suit\":1}],\"top\":{\"rank\":10,\"suit\":1},\"size\":3},\"handBefore\":[{\"rank\":5,\"suit\":2},{\"rank\":0,\"suit\":3},{\"rank\":3,\"suit\":2},{\"rank\":2,\"suit\":0},{\"rank\":0,\"suit\":2},{\"rank\":8,\"suit\":1},{\"rank\":3,\"suit\":1},{\"rank\":6,\"suit\":3},{\"rank\":6,\"suit\":1},{\"rank\":11,\"suit\":2},{\"rank\":8,\"suit\":3},{\"rank\":10,\"suit\":1},{\"rank\":9,\"suit\":0}],\"handSizesBefore\":[10,13],\"handSizesAfter\":[10,10],\"currentComboBefore\":{\"type\":\"seq\",\"cards\":[{\"rank\":2,\"suit\":1},{\"rank\":1,\"suit\":3},{\"rank\":0,\"suit\":0}],\"top\":{\"rank\":2,\"suit\":1},\"size\":3},\"currentComboAfter\":{\"type\":\"seq\",\"cards\":[{\"rank\":10,\"suit\":1},{\"rank\":9,\"suit\":0},{\"rank\":8,\"suit\":1}],\"top\":{\"rank\":10,\"suit\":1},\"size\":3},\"currentPlayerBefore\":1,\"currentPlayerAfter\":0,\"isFirstLead\":false,\"passedFlagsBefore\":[false,false],\"finishedFlagsAfter\":[false,false],\"legalsCount\":3,\"legals\":[[{\"rank\":8,\"suit\":1},{\"rank\":9,\"suit\":0},{\"rank\":10,\"suit\":1}],[{\"rank\":8,\"suit\":3},{\"rank\":9,\"suit\":0},{\"rank\":10,\"suit\":1}],[{\"rank\":9,\"suit\":0},{\"rank\":10,\"suit\":1},{\"rank\":11,\"suit\":2}]],\"publicHistoryLen\":1,\"humanThinkMs\":null,\"ai\":{\"thinkMs\":0,\"stats\":null,\"fallbackUsed\":true,\"error\":null,\"fallbackReason\":\"cheap-force\",\"choice\":[{\"rank\":8,\"suit\":1},{\"rank\":9,\"suit\":0},{\"rank\":10,\"suit\":1}],\"difficulty\":\"grandmaster\"},\"note\":null,\"roundOver\":false,\"finishOrder\":[]},{\"i\":3,\"t\":134837,\"wall\":\"2026-07-11T16:19:24.914Z\",\"type\":\"play\",\"seat\":0,\"actor\":\"human\",\"cards\":[{\"rank\":10,\"suit\":3},{\"rank\":8,\"suit\":2},{\"rank\":9,\"suit\":2}],\"cardsSig\":\"34,38,43\",\"combo\":{\"type\":\"seq\",\"cards\":[{\"rank\":10,\"suit\":3},{\"rank\":9,\"suit\":2},{\"rank\":8,\"suit\":2}],\"top\":{\"rank\":10,\"suit\":3},\"size\":3},\"handBefore\":[{\"rank\":7,\"suit\":2},{\"rank\":10,\"suit\":3},{\"rank\":8,\"suit\":2},{\"rank\":1,\"suit\":0},{\"rank\":9,\"suit\":2},{\"rank\":4,\"suit\":3},{\"rank\":12,\"suit\":3},{\"rank\":8,\"suit\":0},{\"rank\":11,\"suit\":0},{\"rank\":2,\"suit\":3}],\"handSizesBefore\":[10,10],\"handSizesAfter\":[7,10],\"currentComboBefore\":{\"type\":\"seq\",\"cards\":[{\"rank\":10,\"suit\":1},{\"rank\":9,\"suit\":0},{\"rank\":8,\"suit\":1}],\"top\":{\"rank\":10,\"suit\":1},\"size\":3},\"currentComboAfter\":{\"type\":\"seq\",\"cards\":[{\"rank\":10,\"suit\":3},{\"rank\":9,\"suit\":2},{\"rank\":8,\"suit\":2}],\"top\":{\"rank\":10,\"suit\":3},\"size\":3},\"currentPlayerBefore\":0,\"currentPlayerAfter\":1,\"isFirstLead\":false,\"passedFlagsBefore\":[false,false],\"finishedFlagsAfter\":[false,false],\"legalsCount\":4,\"legals\":[[{\"rank\":8,\"suit\":2},{\"rank\":9,\"suit\":2},{\"rank\":10,\"suit\":3}],[{\"rank\":8,\"suit\":0},{\"rank\":9,\"suit\":2},{\"rank\":10,\"suit\":3}],[{\"rank\":9,\"suit\":2},{\"rank\":10,\"suit\":3},{\"rank\":11,\"suit\":0}],[{\"rank\":10,\"suit\":3},{\"rank\":11,\"suit\":0},{\"rank\":12,\"suit\":3}]],\"publicHistoryLen\":2,\"humanThinkMs\":24958,\"ai\":null,\"note\":null,\"roundOver\":false,\"finishOrder\":[]},{\"i\":4,\"t\":135131,\"wall\":\"2026-07-11T16:19:25.208Z\",\"type\":\"pass\",\"seat\":1,\"actor\":\"ai\",\"cards\":null,\"cardsSig\":\"PASS\",\"combo\":null,\"handBefore\":[{\"rank\":5,\"suit\":2},{\"rank\":0,\"suit\":3},{\"rank\":3,\"suit\":2},{\"rank\":2,\"suit\":0},{\"rank\":0,\"suit\":2},{\"rank\":3,\"suit\":1},{\"rank\":6,\"suit\":3},{\"rank\":6,\"suit\":1},{\"rank\":11,\"suit\":2},{\"rank\":8,\"suit\":3}],\"handSizesBefore\":[7,10],\"handSizesAfter\":[7,10],\"currentComboBefore\":{\"type\":\"seq\",\"cards\":[{\"rank\":10,\"suit\":3},{\"rank\":9,\"suit\":2},{\"rank\":8,\"suit\":2}],\"top\":{\"rank\":10,\"suit\":3},\"size\":3},\"currentComboAfter\":null,\"currentPlayerBefore\":1,\"currentPlayerAfter\":0,\"isFirstLead\":false,\"passedFlagsBefore\":[false,false],\"finishedFlagsAfter\":[false,false],\"legalsCount\":0,\"legals\":[],\"publicHistoryLen\":3,\"humanThinkMs\":null,\"ai\":{\"thinkMs\":0,\"stats\":null,\"fallbackUsed\":false,\"error\":null,\"reason\":\"no-legals\"},\"note\":null,\"roundOver\":false,\"finishOrder\":[]},{\"i\":5,\"t\":142532,\"wall\":\"2026-07-11T16:19:32.609Z\",\"type\":\"play\",\"seat\":0,\"actor\":\"human\",\"cards\":[{\"rank\":1,\"suit\":0}],\"cardsSig\":\"4\",\"combo\":{\"type\":\"single\",\"cards\":[{\"rank\":1,\"suit\":0}],\"top\":{\"rank\":1,\"suit\":0},\"size\":1},\"handBefore\":[{\"rank\":7,\"suit\":2},{\"rank\":1,\"suit\":0},{\"rank\":4,\"suit\":3},{\"rank\":12,\"suit\":3},{\"rank\":8,\"suit\":0},{\"rank\":11,\"suit\":0},{\"rank\":2,\"suit\":3}],\"handSizesBefore\":[7,10],\"handSizesAfter\":[6,10],\"currentComboBefore\":null,\"currentComboAfter\":{\"type\":\"single\",\"cards\":[{\"rank\":1,\"suit\":0}],\"top\":{\"rank\":1,\"suit\":0},\"size\":1},\"currentPlayerBefore\":0,\"currentPlayerAfter\":1,\"isFirstLead\":false,\"passedFlagsBefore\":[false,false],\"finishedFlagsAfter\":[false,false],\"legalsCount\":7,\"legals\":[[{\"rank\":7,\"suit\":2}],[{\"rank\":1,\"suit\":0}],[{\"rank\":4,\"suit\":3}],[{\"rank\":12,\"suit\":3}],[{\"rank\":8,\"suit\":0}],[{\"rank\":11,\"suit\":0}],[{\"rank\":2,\"suit\":3}]],\"publicHistoryLen\":4,\"humanThinkMs\":7401,\"ai\":null,\"note\":null,\"roundOver\":false,\"finishOrder\":[]},{\"i\":6,\"t\":142826,\"wall\":\"2026-07-11T16:19:32.903Z\",\"type\":\"play\",\"seat\":1,\"actor\":\"ai\",\"cards\":[{\"rank\":2,\"suit\":0}],\"cardsSig\":\"8\",\"combo\":{\"type\":\"single\",\"cards\":[{\"rank\":2,\"suit\":0}],\"top\":{\"rank\":2,\"suit\":0},\"size\":1},\"handBefore\":[{\"rank\":5,\"suit\":2},{\"rank\":0,\"suit\":3},{\"rank\":3,\"suit\":2},{\"rank\":2,\"suit\":0},{\"rank\":0,\"suit\":2},{\"rank\":3,\"suit\":1},{\"rank\":6,\"suit\":3},{\"rank\":6,\"suit\":1},{\"rank\":11,\"suit\":2},{\"rank\":8,\"suit\":3}],\"handSizesBefore\":[6,10],\"handSizesAfter\":[6,9],\"currentComboBefore\":{\"type\":\"single\",\"cards\":[{\"rank\":1,\"suit\":0}],\"top\":{\"rank\":1,\"suit\":0},\"size\":1},\"currentComboAfter\":{\"type\":\"single\",\"cards\":[{\"rank\":2,\"suit\":0}],\"top\":{\"rank\":2,\"suit\":0},\"size\":1},\"currentPlayerBefore\":1,\"currentPlayerAfter\":0,\"isFirstLead\":false,\"passedFlagsBefore\":[false,false],\"finishedFlagsAfter\":[false,false],\"legalsCount\":8,\"legals\":[[{\"rank\":5,\"suit\":2}],[{\"rank\":3,\"suit\":2}],[{\"rank\":2,\"suit\":0}],[{\"rank\":3,\"suit\":1}],[{\"rank\":6,\"suit\":3}],[{\"rank\":6,\"suit\":1}],[{\"rank\":11,\"suit\":2}],[{\"rank\":8,\"suit\":3}]],\"publicHistoryLen\":5,\"humanThinkMs\":null,\"ai\":{\"thinkMs\":0,\"stats\":null,\"fallbackUsed\":true,\"error\":null,\"fallbackReason\":\"cheap-force\",\"choice\":[{\"rank\":2,\"suit\":0}],\"difficulty\":\"grandmaster\"},\"note\":null,\"roundOver\":false,\"finishOrder\":[]},{\"i\":7,\"t\":146276,\"wall\":\"2026-07-11T16:19:36.353Z\",\"type\":\"play\",\"seat\":0,\"actor\":\"human\",\"cards\":[{\"rank\":2,\"suit\":3}],\"cardsSig\":\"11\",\"combo\":{\"type\":\"single\",\"cards\":[{\"rank\":2,\"suit\":3}],\"top\":{\"rank\":2,\"suit\":3},\"size\":1},\"handBefore\":[{\"rank\":7,\"suit\":2},{\"rank\":4,\"suit\":3},{\"rank\":12,\"suit\":3},{\"rank\":8,\"suit\":0},{\"rank\":11,\"suit\":0},{\"rank\":2,\"suit\":3}],\"handSizesBefore\":[6,9],\"handSizesAfter\":[5,9],\"currentComboBefore\":{\"type\":\"single\",\"cards\":[{\"rank\":2,\"suit\":0}],\"top\":{\"rank\":2,\"suit\":0},\"size\":1},\"currentComboAfter\":{\"type\":\"single\",\"cards\":[{\"rank\":2,\"suit\":3}],\"top\":{\"rank\":2,\"suit\":3},\"size\":1},\"currentPlayerBefore\":0,\"currentPlayerAfter\":1,\"isFirstLead\":false,\"passedFlagsBefore\":[false,false],\"finishedFlagsAfter\":[false,false],\"legalsCount\":6,\"legals\":[[{\"rank\":7,\"suit\":2}],[{\"rank\":4,\"suit\":3}],[{\"rank\":12,\"suit\":3}],[{\"rank\":8,\"suit\":0}],[{\"rank\":11,\"suit\":0}],[{\"rank\":2,\"suit\":3}]],\"publicHistoryLen\":6,\"humanThinkMs\":3449,\"ai\":null,\"note\":null,\"roundOver\":false,\"finishOrder\":[]},{\"i\":8,\"t\":146567,\"wall\":\"2026-07-11T16:19:36.644Z\",\"type\":\"play\",\"seat\":1,\"actor\":\"ai\",\"cards\":[{\"rank\":3,\"suit\":2}],\"cardsSig\":\"14\",\"combo\":{\"type\":\"single\",\"cards\":[{\"rank\":3,\"suit\":2}],\"top\":{\"rank\":3,\"suit\":2},\"size\":1},\"handBefore\":[{\"rank\":5,\"suit\":2},{\"rank\":0,\"suit\":3},{\"rank\":3,\"suit\":2},{\"rank\":0,\"suit\":2},{\"rank\":3,\"suit\":1},{\"rank\":6,\"suit\":3},{\"rank\":6,\"suit\":1},{\"rank\":11,\"suit\":2},{\"rank\":8,\"suit\":3}],\"handSizesBefore\":[5,9],\"handSizesAfter\":[5,8],\"currentComboBefore\":{\"type\":\"single\",\"cards\":[{\"rank\":2,\"suit\":3}],\"top\":{\"rank\":2,\"suit\":3},\"size\":1},\"currentComboAfter\":{\"type\":\"single\",\"cards\":[{\"rank\":3,\"suit\":2}],\"top\":{\"rank\":3,\"suit\":2},\"size\":1},\"currentPlayerBefore\":1,\"currentPlayerAfter\":0,\"isFirstLead\":false,\"passedFlagsBefore\":[false,false],\"finishedFlagsAfter\":[false,false],\"legalsCount\":7,\"legals\":[[{\"rank\":5,\"suit\":2}],[{\"rank\":3,\"suit\":2}],[{\"rank\":3,\"suit\":1}],[{\"rank\":6,\"suit\":3}],[{\"rank\":6,\"suit\":1}],[{\"rank\":11,\"suit\":2}],[{\"rank\":8,\"suit\":3}]],\"publicHistoryLen\":7,\"humanThinkMs\":null,\"ai\":{\"thinkMs\":0,\"stats\":null,\"fallbackUsed\":true,\"error\":null,\"fallbackReason\":\"cheap-force\",\"choice\":[{\"rank\":3,\"suit\":2}],\"difficulty\":\"grandmaster\"},\"note\":null,\"roundOver\":false,\"finishOrder\":[]},{\"i\":9,\"t\":149752,\"wall\":\"2026-07-11T16:19:39.829Z\",\"type\":\"play\",\"seat\":0,\"actor\":\"human\",\"cards\":[{\"rank\":4,\"suit\":3}],\"cardsSig\":\"19\",\"combo\":{\"type\":\"single\",\"cards\":[{\"rank\":4,\"suit\":3}],\"top\":{\"rank\":4,\"suit\":3},\"size\":1},\"handBefore\":[{\"rank\":7,\"suit\":2},{\"rank\":4,\"suit\":3},{\"rank\":12,\"suit\":3},{\"rank\":8,\"suit\":0},{\"rank\":11,\"suit\":0}],\"handSizesBefore\":[5,8],\"handSizesAfter\":[4,8],\"currentComboBefore\":{\"type\":\"single\",\"cards\":[{\"rank\":3,\"suit\":2}],\"top\":{\"rank\":3,\"suit\":2},\"size\":1},\"currentComboAfter\":{\"type\":\"single\",\"cards\":[{\"rank\":4,\"suit\":3}],\"top\":{\"rank\":4,\"suit\":3},\"size\":1},\"currentPlayerBefore\":0,\"currentPlayerAfter\":1,\"isFirstLead\":false,\"passedFlagsBefore\":[false,false],\"finishedFlagsAfter\":[false,false],\"legalsCount\":5,\"legals\":[[{\"rank\":7,\"suit\":2}],[{\"rank\":4,\"suit\":3}],[{\"rank\":12,\"suit\":3}],[{\"rank\":8,\"suit\":0}],[{\"rank\":11,\"suit\":0}]],\"publicHistoryLen\":8,\"humanThinkMs\":3184,\"ai\":null,\"note\":null,\"roundOver\":false,\"finishOrder\":[]},{\"i\":10,\"t\":150043,\"wall\":\"2026-07-11T16:19:40.120Z\",\"type\":\"play\",\"seat\":1,\"actor\":\"ai\",\"cards\":[{\"rank\":5,\"suit\":2}],\"cardsSig\":\"22\",\"combo\":{\"type\":\"single\",\"cards\":[{\"rank\":5,\"suit\":2}],\"top\":{\"rank\":5,\"suit\":2},\"size\":1},\"handBefore\":[{\"rank\":5,\"suit\":2},{\"rank\":0,\"suit\":3},{\"rank\":0,\"suit\":2},{\"rank\":3,\"suit\":1},{\"rank\":6,\"suit\":3},{\"rank\":6,\"suit\":1},{\"rank\":11,\"suit\":2},{\"rank\":8,\"suit\":3}],\"handSizesBefore\":[4,8],\"handSizesAfter\":[4,7],\"currentComboBefore\":{\"type\":\"single\",\"cards\":[{\"rank\":4,\"suit\":3}],\"top\":{\"rank\":4,\"suit\":3},\"size\":1},\"currentComboAfter\":{\"type\":\"single\",\"cards\":[{\"rank\":5,\"suit\":2}],\"top\":{\"rank\":5,\"suit\":2},\"size\":1},\"currentPlayerBefore\":1,\"currentPlayerAfter\":0,\"isFirstLead\":false,\"passedFlagsBefore\":[false,false],\"finishedFlagsAfter\":[false,false],\"legalsCount\":5,\"legals\":[[{\"rank\":5,\"suit\":2}],[{\"rank\":6,\"suit\":3}],[{\"rank\":6,\"suit\":1}],[{\"rank\":11,\"suit\":2}],[{\"rank\":8,\"suit\":3}]],\"publicHistoryLen\":9,\"humanThinkMs\":null,\"ai\":{\"thinkMs\":0,\"stats\":null,\"fallbackUsed\":true,\"error\":null,\"fallbackReason\":\"cheap-force\",\"choice\":[{\"rank\":5,\"suit\":2}],\"difficulty\":\"grandmaster\"},\"note\":null,\"roundOver\":false,\"finishOrder\":[]},{\"i\":11,\"t\":172675,\"wall\":\"2026-07-11T16:20:02.752Z\",\"type\":\"play\",\"seat\":0,\"actor\":\"human\",\"cards\":[{\"rank\":7,\"suit\":2}],\"cardsSig\":\"30\",\"combo\":{\"type\":\"single\",\"cards\":[{\"rank\":7,\"suit\":2}],\"top\":{\"rank\":7,\"suit\":2},\"size\":1},\"handBefore\":[{\"rank\":7,\"suit\":2},{\"rank\":12,\"suit\":3},{\"rank\":8,\"suit\":0},{\"rank\":11,\"suit\":0}],\"handSizesBefore\":[4,7],\"handSizesAfter\":[3,7],\"currentComboBefore\":{\"type\":\"single\",\"cards\":[{\"rank\":5,\"suit\":2}],\"top\":{\"rank\":5,\"suit\":2},\"size\":1},\"currentComboAfter\":{\"type\":\"single\",\"cards\":[{\"rank\":7,\"suit\":2}],\"top\":{\"rank\":7,\"suit\":2},\"size\":1},\"currentPlayerBefore\":0,\"currentPlayerAfter\":1,\"isFirstLead\":false,\"passedFlagsBefore\":[false,false],\"finishedFlagsAfter\":[false,false],\"legalsCount\":4,\"legals\":[[{\"rank\":7,\"suit\":2}],[{\"rank\":12,\"suit\":3}],[{\"rank\":8,\"suit\":0}],[{\"rank\":11,\"suit\":0}]],\"publicHistoryLen\":10,\"humanThinkMs\":22632,\"ai\":null,\"note\":null,\"roundOver\":false,\"finishOrder\":[]},{\"i\":12,\"t\":172965,\"wall\":\"2026-07-11T16:20:03.042Z\",\"type\":\"play\",\"seat\":1,\"actor\":\"ai\",\"cards\":[{\"rank\":8,\"suit\":3}],\"cardsSig\":\"35\",\"combo\":{\"type\":\"single\",\"cards\":[{\"rank\":8,\"suit\":3}],\"top\":{\"rank\":8,\"suit\":3},\"size\":1},\"handBefore\":[{\"rank\":0,\"suit\":3},{\"rank\":0,\"suit\":2},{\"rank\":3,\"suit\":1},{\"rank\":6,\"suit\":3},{\"rank\":6,\"suit\":1},{\"rank\":11,\"suit\":2},{\"rank\":8,\"suit\":3}],\"handSizesBefore\":[3,7],\"handSizesAfter\":[3,6],\"currentComboBefore\":{\"type\":\"single\",\"cards\":[{\"rank\":7,\"suit\":2}],\"top\":{\"rank\":7,\"suit\":2},\"size\":1},\"currentComboAfter\":{\"type\":\"single\",\"cards\":[{\"rank\":8,\"suit\":3}],\"top\":{\"rank\":8,\"suit\":3},\"size\":1},\"currentPlayerBefore\":1,\"currentPlayerAfter\":0,\"isFirstLead\":false,\"passedFlagsBefore\":[false,false],\"finishedFlagsAfter\":[false,false],\"legalsCount\":2,\"legals\":[[{\"rank\":11,\"suit\":2}],[{\"rank\":8,\"suit\":3}]],\"publicHistoryLen\":11,\"humanThinkMs\":null,\"ai\":{\"thinkMs\":0,\"stats\":null,\"fallbackUsed\":true,\"error\":null,\"fallbackReason\":\"cheap-force\",\"choice\":[{\"rank\":8,\"suit\":3}],\"difficulty\":\"grandmaster\"},\"note\":null,\"roundOver\":false,\"finishOrder\":[]},{\"i\":13,\"t\":177286,\"wall\":\"2026-07-11T16:20:07.363Z\",\"type\":\"play\",\"seat\":0,\"actor\":\"human\",\"cards\":[{\"rank\":11,\"suit\":0}],\"cardsSig\":\"44\",\"combo\":{\"type\":\"single\",\"cards\":[{\"rank\":11,\"suit\":0}],\"top\":{\"rank\":11,\"suit\":0},\"size\":1},\"handBefore\":[{\"rank\":12,\"suit\":3},{\"rank\":8,\"suit\":0},{\"rank\":11,\"suit\":0}],\"handSizesBefore\":[3,6],\"handSizesAfter\":[2,6],\"currentComboBefore\":{\"type\":\"single\",\"cards\":[{\"rank\":8,\"suit\":3}],\"top\":{\"rank\":8,\"suit\":3},\"size\":1},\"currentComboAfter\":{\"type\":\"single\",\"cards\":[{\"rank\":11,\"suit\":0}],\"top\":{\"rank\":11,\"suit\":0},\"size\":1},\"currentPlayerBefore\":0,\"currentPlayerAfter\":1,\"isFirstLead\":false,\"passedFlagsBefore\":[false,false],\"finishedFlagsAfter\":[false,false],\"legalsCount\":2,\"legals\":[[{\"rank\":12,\"suit\":3}],[{\"rank\":11,\"suit\":0}]],\"publicHistoryLen\":12,\"humanThinkMs\":4321,\"ai\":null,\"note\":null,\"roundOver\":false,\"finishOrder\":[]},{\"i\":14,\"t\":177576,\"wall\":\"2026-07-11T16:20:07.653Z\",\"type\":\"play\",\"seat\":1,\"actor\":\"ai\",\"cards\":[{\"rank\":11,\"suit\":2}],\"cardsSig\":\"46\",\"combo\":{\"type\":\"single\",\"cards\":[{\"rank\":11,\"suit\":2}],\"top\":{\"rank\":11,\"suit\":2},\"size\":1},\"handBefore\":[{\"rank\":0,\"suit\":3},{\"rank\":0,\"suit\":2},{\"rank\":3,\"suit\":1},{\"rank\":6,\"suit\":3},{\"rank\":6,\"suit\":1},{\"rank\":11,\"suit\":2}],\"handSizesBefore\":[2,6],\"handSizesAfter\":[2,5],\"currentComboBefore\":{\"type\":\"single\",\"cards\":[{\"rank\":11,\"suit\":0}],\"top\":{\"rank\":11,\"suit\":0},\"size\":1},\"currentComboAfter\":{\"type\":\"single\",\"cards\":[{\"rank\":11,\"suit\":2}],\"top\":{\"rank\":11,\"suit\":2},\"size\":1},\"currentPlayerBefore\":1,\"currentPlayerAfter\":0,\"isFirstLead\":false,\"passedFlagsBefore\":[false,false],\"finishedFlagsAfter\":[false,false],\"legalsCount\":1,\"legals\":[[{\"rank\":11,\"suit\":2}]],\"publicHistoryLen\":13,\"humanThinkMs\":null,\"ai\":{\"thinkMs\":0,\"stats\":null,\"fallbackUsed\":true,\"error\":null,\"fallbackReason\":\"cheap-force\",\"choice\":[{\"rank\":11,\"suit\":2}],\"difficulty\":\"grandmaster\"},\"note\":null,\"roundOver\":false,\"finishOrder\":[]},{\"i\":15,\"t\":182445,\"wall\":\"2026-07-11T16:20:12.522Z\",\"type\":\"play\",\"seat\":0,\"actor\":\"human\",\"cards\":[{\"rank\":12,\"suit\":3}],\"cardsSig\":\"51\",\"combo\":{\"type\":\"single\",\"cards\":[{\"rank\":12,\"suit\":3}],\"top\":{\"rank\":12,\"suit\":3},\"size\":1},\"handBefore\":[{\"rank\":12,\"suit\":3},{\"rank\":8,\"suit\":0}],\"handSizesBefore\":[2,5],\"handSizesAfter\":[1,5],\"currentComboBefore\":{\"type\":\"single\",\"cards\":[{\"rank\":11,\"suit\":2}],\"top\":{\"rank\":11,\"suit\":2},\"size\":1},\"currentComboAfter\":{\"type\":\"single\",\"cards\":[{\"rank\":12,\"suit\":3}],\"top\":{\"rank\":12,\"suit\":3},\"size\":1},\"currentPlayerBefore\":0,\"currentPlayerAfter\":1,\"isFirstLead\":false,\"passedFlagsBefore\":[false,false],\"finishedFlagsAfter\":[false,false],\"legalsCount\":1,\"legals\":[[{\"rank\":12,\"suit\":3}]],\"publicHistoryLen\":14,\"humanThinkMs\":4869,\"ai\":null,\"note\":null,\"roundOver\":false,\"finishOrder\":[]},{\"i\":16,\"t\":182732,\"wall\":\"2026-07-11T16:20:12.809Z\",\"type\":\"pass\",\"seat\":1,\"actor\":\"ai\",\"cards\":null,\"cardsSig\":\"PASS\",\"combo\":null,\"handBefore\":[{\"rank\":0,\"suit\":3},{\"rank\":0,\"suit\":2},{\"rank\":3,\"suit\":1},{\"rank\":6,\"suit\":3},{\"rank\":6,\"suit\":1}],\"handSizesBefore\":[1,5],\"handSizesAfter\":[1,5],\"currentComboBefore\":{\"type\":\"single\",\"cards\":[{\"rank\":12,\"suit\":3}],\"top\":{\"rank\":12,\"suit\":3},\"size\":1},\"currentComboAfter\":null,\"currentPlayerBefore\":1,\"currentPlayerAfter\":0,\"isFirstLead\":false,\"passedFlagsBefore\":[false,false],\"finishedFlagsAfter\":[false,false],\"legalsCount\":0,\"legals\":[],\"publicHistoryLen\":15,\"humanThinkMs\":null,\"ai\":{\"thinkMs\":0,\"stats\":null,\"fallbackUsed\":false,\"error\":null,\"reason\":\"no-legals\"},\"note\":null,\"roundOver\":false,\"finishOrder\":[]},{\"i\":17,\"t\":188233,\"wall\":\"2026-07-11T16:20:18.310Z\",\"type\":\"play\",\"seat\":0,\"actor\":\"human\",\"cards\":[{\"rank\":8,\"suit\":0}],\"cardsSig\":\"32\",\"combo\":{\"type\":\"single\",\"cards\":[{\"rank\":8,\"suit\":0}],\"top\":{\"rank\":8,\"suit\":0},\"size\":1},\"handBefore\":[{\"rank\":8,\"suit\":0}],\"handSizesBefore\":[1,5],\"handSizesAfter\":[0,5],\"currentComboBefore\":null,\"currentComboAfter\":{\"type\":\"single\",\"cards\":[{\"rank\":8,\"suit\":0}],\"top\":{\"rank\":8,\"suit\":0},\"size\":1},\"currentPlayerBefore\":0,\"currentPlayerAfter\":1,\"isFirstLead\":false,\"passedFlagsBefore\":[false,false],\"finishedFlagsAfter\":[true,false],\"legalsCount\":1,\"legals\":[[{\"rank\":8,\"suit\":0}]],\"publicHistoryLen\":16,\"humanThinkMs\":5500,\"ai\":null,\"note\":null,\"roundOver\":true,\"finishOrder\":[0]},{\"i\":18,\"t\":188235,\"wall\":\"2026-07-11T16:20:18.312Z\",\"type\":\"game_end\",\"actor\":\"system\",\"result\":{\"finishOrder\":[0],\"loser\":1,\"winner\":0,\"humanWon\":true,\"abandoned\":false,\"reason\":null,\"steps\":17,\"durationMs\":188235,\"eventCount\":18}}],\"result\":{\"finishOrder\":[0],\"loser\":1,\"winner\":0,\"humanWon\":true,\"abandoned\":false,\"reason\":null,\"steps\":17,\"durationMs\":188235,\"eventCount\":18},\"tags\":[\"begin\"],\"notes\":\"\"}\n```\n",
  "closed_by": null,
  "reactions": {
    "url": "https://api.github.com/repos/jvhoang/tieng-len/issues/82/reactions",
    "total_count": 0,
    "+1": 0,
    "-1": 0,
    "laugh": 0,
    "hooray": 0,
    "confused": 0,
    "heart": 0,
    "rocket": 0,
    "eyes": 0
  },
  "timeline_url": "https://api.github.com/repos/jvhoang/tieng-len/issues/82/timeline",
  "performed_via_github_app": null,
  "state_reason": null,
  "pinned_comment": null
}